README.rst
setup.py
sulekha_holtwinters/__init__.py
sulekha_holtwinters/data
sulekha_holtwinters/holtwinters.py
sulekha_holtwinters/holtwinters_1.py
sulekha_holtwinters.egg-info/PKG-INFO
sulekha_holtwinters.egg-info/SOURCES.txt
sulekha_holtwinters.egg-info/dependency_links.txt
sulekha_holtwinters.egg-info/requires.txt
sulekha_holtwinters.egg-info/top_level.txt