Metadata-Version: 1.1
Name: sulekha-holtwinters
Version: 1.4.0
Summary: A Holt Winters implementation Python project
Home-page: https://github.com/sulekhaaloorravi-python/sulekha_holtwinters
Author: Sulekha Aloorravi
Author-email: sulekha.aloorravi@gmail.com
License: UNKNOWN
Keywords: Holt Winters Forecasting Experiment
Platform: UNKNOWN
Classifier: Development Status :: 3 - Alpha
Classifier: Intended Audience :: Developers
Classifier: Intended Audience :: Science/Researc
Classifier: Topic :: Scientific/Engineering :: MathematicsLicense :: OSI Approved :: MIT License
Classifier: Programming Language :: Python :: 2
Classifier: Programming Language :: Python :: 2.7
Classifier: Programming Language :: Python :: 3
Classifier: Programming Language :: Python :: 3.4
Classifier: Programming Language :: Python :: 3.5
Classifier: Programming Language :: Python :: 3.6
Classifier: Programming Language :: Python :: 3.7
